xlavm_lib/__init__.py
xlavm_lib/allure_report/allure_report.py
xlavm_lib/allure_report/browserstack.py
xlavm_lib/allure_report/video_recorder_mobile.py
xlavm_lib/allure_report/video_recorder_web.py
xlavm_lib/get_ids/get_ids.py
xlavm_lib/visual_test/visual_test.py
xlavm_lib/visual_test/visual_test_report.py
xlavm_lib-1.1.1.dist-info/METADATA
xlavm_lib-1.1.1.dist-info/WHEEL
xlavm_lib-1.1.1.dist-info/top_level.txt
xlavm_lib-1.1.1.dist-info/RECORD
