Metadata-Version: 2.4
Name: xlavm-lib
Version: 1.1.1
Summary: Visual Testing and Get Ids utilities for Selenium & Appium
Author-email: Luis Angel Vanegas Martinez <angelvamart@hotmail.com>
License: MIT
Requires-Python: >=3.9
Requires-Dist: pillow
Requires-Dist: opencv-python
Requires-Dist: easyocr
Requires-Dist: jinja2
Requires-Dist: numpy
Requires-Dist: lxml
Requires-Dist: imageio-ffmpeg
Requires-Dist: allure-pytest
